warn_transformer/__init__.py
warn_transformer/cli.py
warn_transformer/consolidate.py
warn_transformer/download.py
warn_transformer/integrate.py
warn_transformer/schema.py
warn_transformer/utils.py
warn_transformer/transformers/__init__.py
warn_transformer/transformers/ak.py
warn_transformer/transformers/al.py
warn_transformer/transformers/az.py
warn_transformer/transformers/ca.py
warn_transformer/transformers/co.py
warn_transformer/transformers/ct.py
warn_transformer/transformers/dc.py
warn_transformer/transformers/de.py
warn_transformer/transformers/fl.py
warn_transformer/transformers/ga.py
warn_transformer/transformers/hi.py
warn_transformer/transformers/ia.py
warn_transformer/transformers/id.py
warn_transformer/transformers/il.py
warn_transformer/transformers/in.py
warn_transformer/transformers/ks.py
warn_transformer/transformers/ky.py
warn_transformer/transformers/la.py
warn_transformer/transformers/md.py
warn_transformer/transformers/me.py
warn_transformer/transformers/mi.py
warn_transformer/transformers/mo.py
warn_transformer/transformers/mt.py
warn_transformer/transformers/ne.py
warn_transformer/transformers/nj.py
warn_transformer/transformers/nm.py
warn_transformer/transformers/ny.py
warn_transformer/transformers/oh.py
warn_transformer/transformers/ok.py
warn_transformer/transformers/or.py
warn_transformer/transformers/pa.py
warn_transformer/transformers/ri.py
warn_transformer/transformers/sc.py
warn_transformer/transformers/sd.py
warn_transformer/transformers/tn.py
warn_transformer/transformers/tx.py
warn_transformer/transformers/ut.py
warn_transformer/transformers/va.py
warn_transformer/transformers/vt.py
warn_transformer/transformers/wa.py
warn_transformer/transformers/wi.py
warn_transformer-1.3.326.dist-info/licenses/LICENSE
warn_transformer-1.3.326.dist-info/METADATA
warn_transformer-1.3.326.dist-info/WHEEL
warn_transformer-1.3.326.dist-info/entry_points.txt
warn_transformer-1.3.326.dist-info/top_level.txt
warn_transformer-1.3.326.dist-info/RECORD
