Metadata-Version: 2.4
Name: warn-transformer
Version: 1.3.326
Summary: Consolidate, enrich and analyze the data gathered by warn-scraper
Author-email: Big Local News <biglocalnews@stanford.edu>
License-Expression: Apache-2.0
Project-URL: Documentation, https://warn-transformer.readthedocs.io
Project-URL: Maintainer, https://github.com/biglocalnews
Project-URL: Source, https://github.com/biglocalnews/warn-transformer
Project-URL: Tracker, https://github.com/biglocalnews/warn-transformer/issues
Keywords: WARN Act,scrapers,WARN Act data,WARN Act scrapers
Classifier: Programming Language :: Python :: 3
Requires-Python: >=3.10
License-File: LICENSE
Requires-Dist: bln
Requires-Dist: click
Requires-Dist: jellyfish
Requires-Dist: marshmallow
Dynamic: license-file
